qfactory/__init__.py
qfactory/core.py
qfactory-1.0.1.dist-info/LICENSE
qfactory-1.0.1.dist-info/METADATA
qfactory-1.0.1.dist-info/WHEEL
qfactory-1.0.1.dist-info/top_level.txt
qfactory-1.0.1.dist-info/RECORD
