Metadata-Version: 2.2
Name: qfactory
Version: 1.0.1
Summary: A Qt based ui widget to manage a factories.Factory
Home-page: https://github.com/mikemalinowski/factories
Author: Mike Malinowski
Author-email: mike.external@outlook.com
Classifier: Programming Language :: Python
Classifier: License :: OSI Approved :: MIT License
Classifier: Operating System :: OS Independent
Requires-Python: >3.1.1
License-File: LICENSE
Requires-Dist: qt.py
Requires-Dist: factories
Dynamic: author
Dynamic: author-email
Dynamic: classifier
Dynamic: description
Dynamic: description-content-type
Dynamic: home-page
Dynamic: requires-dist
Dynamic: requires-python
Dynamic: summary
